paraer/__init__.py
paraer/datastrctures.py
paraer/doc.py
paraer/fields.py
paraer/para.py
paraer/test_code_generator.py
paraer/vendor.py
hypersParaer-2.0.1.dist-info/LICENSE
hypersParaer-2.0.1.dist-info/METADATA
hypersParaer-2.0.1.dist-info/WHEEL
hypersParaer-2.0.1.dist-info/top_level.txt
hypersParaer-2.0.1.dist-info/RECORD
